paddle_edl/__init__.py
paddle_edl/collective/__init__.py
paddle_edl/collective/edl_utils.py
paddle_edl/collective/http_store.py
paddle_edl/collective/launch.py
paddle_edl/collective/utils.py
paddle_edl/demo/__init__.py
paddle_edl/demo/collective/__init__.py
paddle_edl/demo/collective/job_client_demo.py
paddle_edl/demo/collective/job_server_demo.py
paddle_edl/discovery/__init__.py
paddle_edl/discovery/consistent_hash.py
paddle_edl/discovery/etcd_client.py
paddle_edl/discovery/register.py
paddle_edl/discovery/server_alive.py
paddle_edl/distill/__init__.py
paddle_edl/distill/balance_table.py
paddle_edl/distill/discovery_client.py
paddle_edl/distill/discovery_server.py
paddle_edl/distill/distill_discovery_pb2.py
paddle_edl/distill/distill_discovery_pb2_grpc.py
paddle_edl/distill/distill_reader.py
paddle_edl/distill/distill_worker.py
paddle_edl/distill/timeline.py
paddle_edl/distill/utils.py
paddle_edl/distill/redis/__init__.py
paddle_edl/distill/redis/balance_server.py
paddle_edl/distill/redis/client.py
paddle_edl/distill/redis/redis_store.py
paddle_edl/distill/redis/server_register.py
paddle_edl/distill/redis/service_table.py
paddle_edl-0.3.1.dist-info/METADATA
paddle_edl-0.3.1.dist-info/WHEEL
paddle_edl-0.3.1.dist-info/top_level.txt
paddle_edl-0.3.1.dist-info/RECORD
